{
	"planetName": "Barnard",
	"minimapSize": 10,
  "xLocation": -2,
  "yLocation": -1,
  "scale": 10,
  "mapGraphic": "Planet4",
	"landingGraphic": "proxima.png",

	"buttons": [true, true, true, true, true],

	"blurb": "A big planet!",

	"tradeDepotStats":{	"food"		:{"buy":50, "sell":62},
	    "medical"	:{"buy":200, "sell":228},
	    "consumerTech"  :{"buy":100, "sell":114}
	    },

	"mechanics"	 :{	"shipyard"	:["Venturer", "Defender"],
	    "outfitter"	:["Light Blaster", "Dodge Module"]
	    },

	"missionBoard"	 :{	"passenger"	: true,
	    "delivery" 	: true,
	    "defend"   	: true
	    }
}

